aacoding_portal_gun/__init__.py
aacoding_portal_gun/__main__.py
aacoding_portal_gun/main.py
aacoding_portal_gun-0.1.0.dist-info/entry_points.txt
aacoding_portal_gun-0.1.0.dist-info/WHEEL
aacoding_portal_gun-0.1.0.dist-info/METADATA
aacoding_portal_gun-0.1.0.dist-info/RECORD
