Metadata-Version: 2.1
Name: aacoding-portal-gun
Version: 0.1.0
Summary: 
Author: Robert Zhou
Author-email: alphacodinghub@outlook.com
Requires-Python: >=3.9,<4.0
Classifier: Programming Language :: Python :: 3
Classifier: Programming Language :: Python :: 3.9
Requires-Dist: typer[all] (>=0.4.0,<0.5.0)
